{
"reportSection" : "Summary",
"reportSections" : [ "Summary", "Detail" ],
"stats" : {
"totalRows:" : 12,
"returnedRows:" : 12,
"userAllowedRows:" : 99999
},
"results" : [ {
"report_date" : "04/06/2022",
"is_correction" : null,
"narrative" : null,
"purchase_type" : "Formula Base",
"dressed_head_count" : "291,683",
"live_head_count" : "52,303",
"total_head_count" : "343,986",
"report_title" : "TX-OK-NM Monthly Direct Slaughter Cattle - Formulated Base and Forward Contract Base Purchases",
"slug_name" : "AMS_3503",
"slug_id" : "3503",
"office_name" : "St Joseph, MO",
"office_code" : "LS-SJ",
"office_city" : "Saint Joseph",
"office_state" : "MO",
"market_location_name" : "St. Joseph, MO",
"market_location_city" : "St. Joseph",
"market_location_state" : "MO",
"market_type" : "Direct Livestock - LMR Cattle",
"market_type_category" : "Direct Livestock - LMR Cattle",
"published_date" : "04/06/2022 09:04:16"
}, {
"report_date" : "04/06/2022",
"is_correction" : null,
"narrative" : null,
"purchase_type" : "Forward Contract Base",
"dressed_head_count" : "5,941",
"live_head_count" : "8,838",
"total_head_count" : "14,779",
"report_title" : "TX-OK-NM Monthly Direct Slaughter Cattle - Formulated Base and Forward Contract Base Purchases",
"slug_name" : "AMS_3503",
"slug_id" : "3503",
"office_name" : "St Joseph, MO",
"office_code" : "LS-SJ",
"office_city" : "Saint Joseph",
"office_state" : "MO",
"market_location_name" : "St. Joseph, MO",
"market_location_city" : "St. Joseph",
"market_location_state" : "MO",
"market_type" : "Direct Livestock - LMR Cattle",
"market_type_category" : "Direct Livestock - LMR Cattle",
"published_date" : "04/06/2022 09:04:16"
}, {
"report_date" : "02/02/2022",
"is_correction" : null,
"narrative" : null,
"purchase_type" : "Formula Base",
"dressed_head_count" : "263,663",
"live_head_count" : "50,764",
"total_head_count" : "314,427",
"report_title" : "TX-OK-NM Monthly Direct Slaughter Cattle - Formulated Base and Forward Contract Base Purchases",
"slug_name" : "AMS_3503",
"slug_id" : "3503",
"office_name" : "St Joseph, MO",
"office_code" : "LS-SJ",
"office_city" : "Saint Joseph",
"office_state" : "MO",
"market_location_name" : "St. Joseph, MO",
"market_location_city" : "St. Joseph",
"market_location_state" : "MO",
"market_type" : "Direct Livestock - LMR Cattle",
"market_type_category" : "Direct Livestock - LMR Cattle",
"published_date" : "02/02/2022 09:43:52"
}, {
"report_date" : "02/02/2022",
"is_correction" : null,
"narrative" : null,
"purchase_type" : "Forward Contract Base",
"dressed_head_count" : "2,910",
"live_head_count" : "5,367",
"total_head_count" : "8,277",
"report_title" : "TX-OK-NM Monthly Direct Slaughter Cattle - Formulated Base and Forward Contract Base Purchases",
"slug_name" : "AMS_3503",
"slug_id" : "3503",
"office_name" : "St Joseph, MO",
"office_code" : "LS-SJ",
"office_city" : "Saint Joseph",
"office_state" : "MO",
"market_location_name" : "St. Joseph, MO",
"market_location_city" : "St. Joseph",
"market_location_state" : "MO",
"market_type" : "Direct Livestock - LMR Cattle",
"market_type_category" : "Direct Livestock - LMR Cattle",
"published_date" : "02/02/2022 09:43:52"
}, {
"report_date" : "12/08/2021",
"is_correction" : null,
"narrative" : null,
"purchase_type" : "Formula Base",
"dressed_head_count" : "272,080",
"live_head_count" : "45,684",
"total_head_count" : "317,764",
"report_title" : "TX-OK-NM Monthly Direct Slaughter Cattle - Formulated Base and Forward Contract Base Purchases",
"slug_name" : "AMS_3503",
"slug_id" : "3503",
"office_name" : "St Joseph, MO",
"office_code" : "LS-SJ",
"office_city" : "Saint Joseph",
"office_state" : "MO",
"market_location_name" : "St. Joseph, MO",
"market_location_city" : "St. Joseph",
"market_location_state" : "MO",
"market_type" : "Direct Livestock - LMR Cattle",
"market_type_category" : "Direct Livestock - LMR Cattle",
"published_date" : "12/08/2021 15:24:39"
}, {
"report_date" : "12/08/2021",
"is_correction" : null,
"narrative" : null,
"purchase_type" : "Forward Contract Base",
"dressed_head_count" : "3,179",
"live_head_count" : "16,143",
"total_head_count" : "19,322",
"report_title" : "TX-OK-NM Monthly Direct Slaughter Cattle - Formulated Base and Forward Contract Base Purchases",
"slug_name" : "AMS_3503",
"slug_id" : "3503",
"office_name" : "St Joseph, MO",
"office_code" : "LS-SJ",
"office_city" : "Saint Joseph",
"office_state" : "MO",
"market_location_name" : "St. Joseph, MO",
"market_location_city" : "St. Joseph",
"market_location_state" : "MO",
"market_type" : "Direct Livestock - LMR Cattle",
"market_type_category" : "Direct Livestock - LMR Cattle",
"published_date" : "12/08/2021 15:24:39"
}, {
"report_date" : "11/09/2021",
"is_correction" : null,
"narrative" : null,
"purchase_type" : "Formula Base",
"dressed_head_count" : "261,768",
"live_head_count" : "49,043",
"total_head_count" : "310,811",
"report_title" : "TX-OK-NM Monthly Direct Slaughter Cattle - Formulated Base and Forward Contract Base Purchases",
"slug_name" : "AMS_3503",
"slug_id" : "3503",
"office_name" : "St Joseph, MO",
"office_code" : "LS-SJ",
"office_city" : "Saint Joseph",
"office_state" : "MO",
"market_location_name" : "St. Joseph, MO",
"market_location_city" : "St. Joseph",
"market_location_state" : "MO",
"market_type" : "Direct Livestock - LMR Cattle",
"market_type_category" : "Direct Livestock - LMR Cattle",
"published_date" : "12/08/2021 14:33:08"
}, {
"report_date" : "11/09/2021",
"is_correction" : null,
"narrative" : null,
"purchase_type" : "Forward Contract Base",
"dressed_head_count" : "1,968",
"live_head_count" : "7,637",
"total_head_count" : "9,605",
"report_title" : "TX-OK-NM Monthly Direct Slaughter Cattle - Formulated Base and Forward Contract Base Purchases",
"slug_name" : "AMS_3503",
"slug_id" : "3503",
"office_name" : "St Joseph, MO",
"office_code" : "LS-SJ",
"office_city" : "Saint Joseph",
"office_state" : "MO",
"market_location_name" : "St. Joseph, MO",
"market_location_city" : "St. Joseph",
"market_location_state" : "MO",
"market_type" : "Direct Livestock - LMR Cattle",
"market_type_category" : "Direct Livestock - LMR Cattle",
"published_date" : "12/08/2021 14:33:08"
}, {
"report_date" : "10/06/2021",
"is_correction" : null,
"narrative" : null,
"purchase_type" : "Formula Base",
"dressed_head_count" : "276,723",
"live_head_count" : "69,171",
"total_head_count" : "345,894",
"report_title" : "TX-OK-NM Monthly Direct Slaughter Cattle - Formulated Base and Forward Contract Base Purchases",
"slug_name" : "AMS_3503",
"slug_id" : "3503",
"office_name" : "St Joseph, MO",
"office_code" : "LS-SJ",
"office_city" : "Saint Joseph",
"office_state" : "MO",
"market_location_name" : "St. Joseph, MO",
"market_location_city" : "St. Joseph",
"market_location_state" : "MO",
"market_type" : "Direct Livestock - LMR Cattle",
"market_type_category" : "Direct Livestock - LMR Cattle",
"published_date" : "10/06/2021 12:31:18"
}, {
"report_date" : "10/06/2021",
"is_correction" : null,
"narrative" : null,
"purchase_type" : "Forward Contract Base",
"dressed_head_count" : "583",
"live_head_count" : "3,476",
"total_head_count" : "4,059",
"report_title" : "TX-OK-NM Monthly Direct Slaughter Cattle - Formulated Base and Forward Contract Base Purchases",
"slug_name" : "AMS_3503",
"slug_id" : "3503",
"office_name" : "St Joseph, MO",
"office_code" : "LS-SJ",
"office_city" : "Saint Joseph",
"office_state" : "MO",
"market_location_name" : "St. Joseph, MO",
"market_location_city" : "St. Joseph",
"market_location_state" : "MO",
"market_type" : "Direct Livestock - LMR Cattle",
"market_type_category" : "Direct Livestock - LMR Cattle",
"published_date" : "10/06/2021 12:31:18"
}, {
"report_date" : "09/03/2021",
"is_correction" : null,
"narrative" : null,
"purchase_type" : "Formula Base",
"dressed_head_count" : "290,074",
"live_head_count" : "80,373",
"total_head_count" : "370,447",
"report_title" : "TX-OK-NM Monthly Direct Slaughter Cattle - Formulated Base and Forward Contract Base Purchases",
"slug_name" : "AMS_3503",
"slug_id" : "3503",
"office_name" : "St Joseph, MO",
"office_code" : "LS-SJ",
"office_city" : "Saint Joseph",
"office_state" : "MO",
"market_location_name" : "St. Joseph, MO",
"market_location_city" : "St. Joseph",
"market_location_state" : "MO",
"market_type" : "Direct Livestock - LMR Cattle",
"market_type_category" : "Direct Livestock - LMR Cattle",
"published_date" : "09/03/2021 13:47:25"
}, {
"report_date" : "09/03/2021",
"is_correction" : null,
"narrative" : null,
"purchase_type" : "Forward Contract Base",
"dressed_head_count" : "6,630",
"live_head_count" : "14,308",
"total_head_count" : "20,938",
"report_title" : "TX-OK-NM Monthly Direct Slaughter Cattle - Formulated Base and Forward Contract Base Purchases",
"slug_name" : "AMS_3503",
"slug_id" : "3503",
"office_name" : "St Joseph, MO",
"office_code" : "LS-SJ",
"office_city" : "Saint Joseph",
"office_state" : "MO",
"market_location_name" : "St. Joseph, MO",
"market_location_city" : "St. Joseph",
"market_location_state" : "MO",
"market_type" : "Direct Livestock - LMR Cattle",
"market_type_category" : "Direct Livestock - LMR Cattle",
"published_date" : "09/03/2021 13:47:25"
} ]
}